micadoparser/__init__.py
micadoparser/cli.py
micadoparser/exceptions.py
micadoparser/parser.py
micadoparser/validations.py
micadoparser/validator.py
micadoparser/utils/csar.py
micadoparser/utils/tosca.py
micadoparser/utils/utils.py
micadoparser/utils/yaml.py
micado_parser-0.12.3.dist-info/LICENSE
micado_parser-0.12.3.dist-info/METADATA
micado_parser-0.12.3.dist-info/WHEEL
micado_parser-0.12.3.dist-info/entry_points.txt
micado_parser-0.12.3.dist-info/top_level.txt
micado_parser-0.12.3.dist-info/RECORD
