Metadata-Version: 2.1
Name: micado-parser
Version: 0.12.3
Summary: Parse MiCADO ADTs for the MiCADO Submitter
Home-page: https://github.com/micado-scale/micado-parser
Author: Jay DesLauriers
Author-email: j.deslauriers@westminster.ac.uk
Project-URL: Bug Tracker, https://github.com/micado-scale/micado-parser/issues
Classifier: Programming Language :: Python :: 3
Classifier: License :: OSI Approved :: Apache Software License
Classifier: Operating System :: OS Independent
Requires-Python: >=3.8
License-File: LICENSE
Requires-Dist: ruamel.yaml
Requires-Dist: tosca-parser
Requires-Dist: click
